botscale/__init__.py
botscale/py.typed
botscale-0.0.1.dist-info/METADATA
botscale-0.0.1.dist-info/WHEEL
botscale-0.0.1.dist-info/top_level.txt
botscale-0.0.1.dist-info/RECORD
