Metadata-Version: 2.4
Name: botscale
Version: 0.0.1
Summary: BotScale - Universal bot framework (name reservation)
Author-email: BotScale Contributors <botscale@users.noreply.github.com>
License: BSL-1.1
Project-URL: Homepage, https://github.com/sensiloles/botscale
Project-URL: Repository, https://github.com/sensiloles/botscale
Project-URL: Documentation, https://github.com/sensiloles/botscale#readme
Classifier: Development Status :: 1 - Planning
Classifier: Intended Audience :: Developers
Classifier: License :: Other/Proprietary License
Classifier: Programming Language :: Python :: 3
Classifier: Programming Language :: Python :: 3.9
Classifier: Programming Language :: Python :: 3.10
Classifier: Programming Language :: Python :: 3.11
Classifier: Programming Language :: Python :: 3.12
Classifier: Topic :: Software Development :: Libraries
Requires-Python: >=3.9
